botostubs/__init__.py
botostubs/py.typed
botostubs-0.15.1.23.10.dist-info/METADATA
botostubs-0.15.1.23.10.dist-info/WHEEL
botostubs-0.15.1.23.10.dist-info/top_level.txt
botostubs-0.15.1.23.10.dist-info/RECORD
