Metadata-Version: 2.1
Name: botostubs
Version: 0.15.1.23.10
Summary: boto3 code assistance for any API in any IDE, always up to date
Home-page: https://github.com/jeshan/botostubs
Author: Jeshan G. BABOOA
Author-email: j@jeshan.co
License: BSD-2-Clause
Platform: UNKNOWN
Classifier: Programming Language :: Python :: 3
Classifier: Programming Language :: Python :: 3.6
Classifier: License :: OSI Approved :: BSD License
Classifier: Operating System :: OS Independent
